{"id": "posix", "path": "/Users/travis/opt/anaconda3/lib/python3.7/site-packages/mypy/typeshed/stdlib/3/posix.pyi", "mtime": 1585307803, "size": 2234, "hash": "444d9bdab04b9b8ea3f239d72ae1c65c5579c9c854302877d2017c1ca0b0d3b7", "data_mtime": 1588166371, "dependencies": ["sys", "typing", "os", "builtins", "abc"], "suppressed": [], "options": {"plugins": [], "disallow_incomplete_defs": false, "disallow_untyped_calls": false, "always_false": [], "mypyc": false, "disallow_subclassing_any": false, "follow_imports": "normal", "follow_imports_for_stubs": false, "no_implicit_optional": false, "disallow_any_generics": false, "disallow_any_explicit": false, "platform": "darwin", "local_partial_types": false, "bazel": false, "implicit_reexport": true, "strict_equality": false, "allow_redefinition": false, "check_untyped_defs": false, "ignore_errors": false, "disallow_any_decorated": false, "disallow_untyped_decorators": false, "warn_unreachable": false, "show_none_errors": true, "disallow_any_unimported": false, "strict_optional": true, "strict_optional_whitelist": null, "disallow_untyped_defs": false, "warn_unused_ignores": false, "warn_no_return": true, "allow_untyped_globals": false, "always_true": [], "warn_return_any": false, "ignore_missing_imports": false, "disallow_any_expr": false}, "dep_prios": [10, 5, 5, 5, 30], "dep_lines": [5, 6, 8, 11, 1], "interface_hash": "f052ee9e2e63afcb67172c920706219844f7ca16393ad43b76777c3bbd16a113", "version_id": "0.770", "ignore_all": true, "plugin_data": null}